{"quantidade": 100, "projetos": [{"valor_aprovado": 399000.0, "valor_captado": 0.0, "nome": "INCLUSÃO MUSICAL INSTRUMENTAL", "cgccpf": "05484715000180", "valor_solicitado": 399000.01, "ano_projeto": "10", "enquadramento": "Artigo 18", "municipio": "Ribeirão Preto", "segmento": "Música Instrumental", "valor_proposta": 399000.01, "UF": "SP", "data_inicio": "2011-01-24", "projetos": 0, "mecanismo": "Mecenato", "data_termino": "2012-01-16", "proponente": "Sociedade Artística Coro Cênico Bossa Nossa", "valor_projeto": 399000.0, "area": "Música", "PRONAC": "108513"}, {"valor_aprovado": 0.0, "valor_captado": 0.0, "nome": "100 Anos de futebol Arte - S.F.C.", "cgccpf": "09073950000110", "valor_solicitado": 1733018.0, "ano_projeto": "10", "enquadramento": "Nao enquadrado", "municipio": "Guarujá", "segmento": "Artes Integradas", "valor_proposta": 1733018.0, "UF": "SP", "data_inicio": "2011-03-11", "projetos": 1, "mecanismo": "Mecenato", "data_termino": "2012-03-11", "proponente": "Instituto Cultural, Ambiental, Educacional - CAE", "valor_projeto": 0.0, "area": "Artes Integradas", "PRONAC": "108512"}, {"valor_aprovado": 6520450.0, "valor_captado": 3089997.21, "nome": "Eu Faço Cultura - Instrumental 2011", "cgccpf": "34267237000155", "valor_solicitado": 6727000.0, "ano_projeto": "10", "enquadramento": "Artigo 18", "municipio": "Brasília", "segmento": "Música Instrumental", "valor_proposta": 6727000.0, "UF": "DF", "data_inicio": "2010-12-18", "projetos": 2, "mecanismo": "Mecenato", "data_termino": "2012-07-12", "proponente": "Federação Nacional das Associações do Pessoal da CEF", "valor_projeto": 6520450.0, "area": "Música", "PRONAC": "108511"}, {"valor_aprovado": 390805.5, "valor_captado": 182924.0, "nome": "O Terceiro Ato - O Teatro Mágico", "cgccpf": "08151402000107", "valor_solicitado": 405339.0, "ano_projeto": "10", "enquadramento": "Artigo 18", "municipio": "Osasco", "segmento": "Restauração/Bolsas", "valor_proposta": 405339.0, "UF": "SP", "data_inicio": "2011-01-03", "projetos": 3, "mecanismo": "Mecenato", "data_termino": "2011-04-30", "proponente": "O Teatro Mágico - Produções Artísticas Ltda.", "valor_projeto": 390805.5, "area": "Artes Integradas", "PRONAC": "108510"}, {"valor_aprovado": 1689460.0, "valor_captado": 0.0, "nome": "Borboletas Apaixonadas", "cgccpf": "09146619000183", "valor_solicitado": 1705210.0, "ano_projeto": "10", "enquadramento": "Artigo 18", "municipio": "São Paulo", "segmento": "Dança", "valor_proposta": 1705210.0, "UF": "SP", "data_inicio": "2011-06-01", "projetos": 4, "mecanismo": "Mecenato", "data_termino": "2012-01-01", "proponente": "Gaia Produtora Ltda", "valor_projeto": 1689460.0, "area": "Artes Cênicas", "PRONAC": "108509"}, {"valor_aprovado": 0.0, "valor_captado": 0.0, "nome": "Orquestra Jovem de Pinda", "cgccpf": "***696638**", "valor_solicitado": 310660.0, "ano_projeto": "10", "enquadramento": "Nao enquadrado", "municipio": "Taubaté", "segmento": "Música Instrumental", "valor_proposta": 310660.0, "UF": "SP", "data_inicio": "2011-01-10", "projetos": 5, "mecanismo": "Mecenato", "data_termino": "2011-12-30", "proponente": "Andre Luis Frade", "valor_projeto": 0.0, "area": "Música", "PRONAC": "108508"}, {"valor_aprovado": 328370.0, "valor_captado": 0.0, "nome": "DVD do Grupo PATUBATÊ", "cgccpf": "05286859000122", "valor_solicitado": 348370.0, "ano_projeto": "10", "enquadramento": "Artigo 18", "municipio": "Brasília", "segmento": "Música Instrumental", "valor_proposta": 348370.0, "UF": "DF", "data_inicio": "2011-01-03", "projetos": 6, "mecanismo": "Mecenato", "data_termino": "2011-03-31", "proponente": "Ossos do Ofício - Confraria das Artes", "valor_projeto": 328370.0, "area": "Música", "PRONAC": "108507"}, {"valor_aprovado": 230190.0, "valor_captado": 0.0, "nome": "Harmonica Brasilis", "cgccpf": "00242382000160", "valor_solicitado": 234190.0, "ano_projeto": "10", "enquadramento": "Artigo 18", "municipio": "Rio de Janeiro", "segmento": "Música Instrumental", "valor_proposta": 234190.0, "UF": "RJ", "data_inicio": "2011-01-01", "projetos": 7, "mecanismo": "Mecenato", "data_termino": "2011-12-31", "proponente": "ACV Produções Culturais Ltda", "valor_projeto": 230190.0, "area": "Música", "PRONAC": "108506"}, {"valor_aprovado": 201896.2, "valor_captado": 0.0, "nome": "Casa da Aldeia - Educação Patrimonial e Divulgação", "cgccpf": "04890904000190", "valor_solicitado": 237496.6, "ano_projeto": "10", "enquadramento": "Artigo 18", "municipio": "Cachoeira do Sul", "segmento": "Edição de Livros", "valor_proposta": 237496.6, "UF": "RS", "data_inicio": "2011-03-21", "projetos": 8, "mecanismo": "Mecenato", "data_termino": "2012-03-21", "proponente": "Defender - Defesa Civil do Patrimônio Histórico", "valor_projeto": 201896.2, "area": "Humanidades", "PRONAC": "108505"}, {"valor_aprovado": 884175.62, "valor_captado": 0.0, "nome": "Farofafá - site de jornalismo musical", "cgccpf": "07276456000128", "valor_solicitado": 981175.62, "ano_projeto": "10", "enquadramento": "Artigo 26", "municipio": "São Paulo", "segmento": "Música Popular Cantada", "valor_proposta": 981175.62, "UF": "SP", "data_inicio": "2011-06-01", "projetos": 9, "mecanismo": "Mecenato", "data_termino": "2013-12-31", "proponente": "PAS Edições de Textos e Produções Culturais LTDA", "valor_projeto": 884175.62, "area": "Música", "PRONAC": "108503"}, {"valor_aprovado": 127398.25, "valor_captado": 0.0, "nome": "Grande Show Beneficente Talentos de Araxá", "cgccpf": "10548421000105", "valor_solicitado": 148960.0, "ano_projeto": "10", "enquadramento": "Artigo 18", "municipio": "Araxá", "segmento": "Artes Integradas", "valor_proposta": 148960.0, "UF": "MG", "data_inicio": "2011-11-14", "projetos": 10, "mecanismo": "Mecenato", "data_termino": "2012-01-31", "proponente": "FUNDAÇÃO CULTURAL ACIA", "valor_projeto": 127398.25, "area": "Artes Integradas", "PRONAC": "108502"}, {"valor_aprovado": 12728759.0, "valor_captado": 0.0, "nome": "Teatro de Inclusão - Edistio José Rebouças Filho", "cgccpf": "06056498000190", "valor_solicitado": 14535575.07, "ano_projeto": "10", "enquadramento": "Artigo 26", "municipio": "São Paulo", "segmento": "Arquitetônico", "valor_proposta": 14535575.07, "UF": "SP", "data_inicio": "2010-11-20", "projetos": 11, "mecanismo": "Mecenato", "data_termino": "2012-06-20", "proponente": "Organização de Desenvolvimento Cultural e Preservação Ambiental - AMA BRASIL", "valor_projeto": 12728759.0, "area": "Patrimônio Cultural", "PRONAC": "108501"}, {"valor_aprovado": 251469.05, "valor_captado": 251469.05, "nome": "CAPOEIRA, CULTURA DA GENTE: JOGA PIÁ ( II EDIÇÃO)", "cgccpf": "09287265000197", "valor_solicitado": 300932.3, "ano_projeto": "10", "enquadramento": "Artigo 18", "municipio": "Pinhais", "segmento": "Dança", "valor_proposta": 300932.3, "UF": "PR", "data_inicio": "2010-12-01", "projetos": 12, "mecanismo": "Mecenato", "data_termino": "2012-01-02", "proponente": "Associação Abadá Capoeira Educacional  e Cultural de PIN", "valor_projeto": 251469.05, "area": "Artes Cênicas", "PRONAC": "108498"}, {"valor_aprovado": 0.0, "valor_captado": 0.0, "nome": "Formação de acervos para bibliotecas", "cgccpf": "02871771000180", "valor_solicitado": 7316217.7, "ano_projeto": "10", "enquadramento": "Nao enquadrado", "municipio": "São Paulo", "segmento": "Acervo", "valor_proposta": 7316217.7, "UF": "SP", "data_inicio": "2010-11-30", "projetos": 13, "mecanismo": "Mecenato", "data_termino": "2011-11-30", "proponente": "Associação Alfabetização Solidária", "valor_projeto": 0.0, "area": "Patrimônio Cultural", "PRONAC": "108497"}, {"valor_aprovado": 234373.07, "valor_captado": 233000.0, "nome": "Caravana Pixaim", "cgccpf": "***865601**", "valor_solicitado": 243728.07, "ano_projeto": "10", "enquadramento": "Artigo 18", "municipio": "Cuiabá", "segmento": "Artes Integradas", "valor_proposta": 243728.07, "UF": "MT", "data_inicio": "2011-01-11", "projetos": 14, "mecanismo": "Mecenato", "data_termino": "2013-12-31", "proponente": "Karina Santiago de Assis", "valor_projeto": 234373.07, "area": "Artes Integradas", "PRONAC": "108492"}, {"valor_aprovado": 441825.0, "valor_captado": 0.0, "nome": "TEATRO DE BONECOS NA PRAÇA", "cgccpf": "04364821000168", "valor_solicitado": 455900.0, "ano_projeto": "10", "enquadramento": "Artigo 18", "municipio": "Rio de Janeiro", "segmento": "Teatro", "valor_proposta": 455900.0, "UF": "RJ", "data_inicio": "2011-03-05", "projetos": 15, "mecanismo": "Mecenato", "data_termino": "2011-10-08", "proponente": "Vertente Cultural CEPETIN - Centro de Pesquisa e Estudo do Teatro Infantil Ltda ME.", "valor_projeto": 441825.0, "area": "Artes Cênicas", "PRONAC": "108491"}, {"valor_aprovado": 0.0, "valor_captado": 0.0, "nome": "Vidas dedicadas ao Brasil", "cgccpf": "11273762000188", "valor_solicitado": 321880.0, "ano_projeto": "10", "enquadramento": "Nao enquadrado", "municipio": "São Paulo", "segmento": "Edição de Livros", "valor_proposta": 321880.0, "UF": "SP", "data_inicio": "2010-11-22", "projetos": 16, "mecanismo": "Mecenato", "data_termino": "2010-12-30", "proponente": "Amora Produções Artisticas Ltda", "valor_projeto": 0.0, "area": "Humanidades", "PRONAC": "108490"}, {"valor_aprovado": 214850.0, "valor_captado": 0.0, "nome": "SE LIGA NA LIGA 2010", "cgccpf": "***334087**", "valor_solicitado": 226850.0, "ano_projeto": "10", "enquadramento": "Artigo 18", "municipio": "Rio de Janeiro", "segmento": "Artes Integradas", "valor_proposta": 226850.0, "UF": "RJ", "data_inicio": "2011-04-21", "projetos": 17, "mecanismo": "Mecenato", "data_termino": "2011-11-20", "proponente": "Joarry Baptista dos Santos", "valor_projeto": 214850.0, "area": "Artes Integradas", "PRONAC": "108489"}, {"valor_aprovado": 10212.5, "valor_captado": 10212.5, "nome": "DRAMATURGIA NAS GERAIS", "cgccpf": "***000876**", "valor_solicitado": 10550.0, "ano_projeto": "10", "enquadramento": "Artigo 18", "municipio": "Uberlândia", "segmento": "Edição de Livros", "valor_proposta": 10550.0, "UF": "MG", "data_inicio": "2010-12-01", "projetos": 18, "mecanismo": "Mecenato", "data_termino": "2011-05-01", "proponente": "FRANCISCO ANTÔNIO DE ALMEIDA", "valor_projeto": 10212.5, "area": "Humanidades", "PRONAC": "108488"}, {"valor_aprovado": 484868.0, "valor_captado": 240000.0, "nome": "CIA. DRUW - MOSTRA DE REPERTÓRIO: LÚDICO & VILA TARSILA", "cgccpf": "08016000000191", "valor_solicitado": 603000.0, "ano_projeto": "10", "enquadramento": "Artigo 18", "municipio": "São Paulo", "segmento": "Dança", "valor_proposta": 603000.0, "UF": "SP", "data_inicio": "2011-01-01", "projetos": 19, "mecanismo": "Mecenato", "data_termino": "2011-12-31", "proponente": "Miriam Druwe Produções Artísticas LTDA", "valor_projeto": 484868.0, "area": "Artes Cênicas", "PRONAC": "108487"}, {"valor_aprovado": 99674.0, "valor_captado": 0.0, "nome": "O SHOW MAIS BONITO DA CIDADE", "cgccpf": "10623434000100", "valor_solicitado": 101774.0, "ano_projeto": "10", "enquadramento": "Artigo 26", "municipio": "Curitiba", "segmento": "Música Popular Cantada", "valor_proposta": 101774.0, "UF": "PR", "data_inicio": "2011-04-04", "projetos": 20, "mecanismo": "Mecenato", "data_termino": "2011-06-30", "proponente": "PRO CULT PROJETOS E EVENTOS CULTURAIS LTDA", "valor_projeto": 99674.0, "area": "Música", "PRONAC": "108485"}, {"valor_aprovado": 519717.35, "valor_captado": 0.0, "nome": "Atletas Paraolímpicos", "cgccpf": "06637230000142", "valor_solicitado": 617053.8, "ano_projeto": "10", "enquadramento": "Artigo 18", "municipio": "Rio de Janeiro", "segmento": "Edição de Livros", "valor_proposta": 617053.8, "UF": "RJ", "data_inicio": "2013-01-01", "projetos": 21, "mecanismo": "Mecenato", "data_termino": "2013-12-31", "proponente": "CARBONO DESIGN, FOTOGRAFIA E TEXTO LTDA ", "valor_projeto": 519717.35, "area": "Humanidades", "PRONAC": "108484"}, {"valor_aprovado": 186950.0, "valor_captado": 50000.0, "nome": "FESTIVAL DE MÚSICA BARROCA DE ALCÂNTARA", "cgccpf": "09310462000180", "valor_solicitado": 766645.0, "ano_projeto": "10", "enquadramento": "Artigo 18", "municipio": "Rio de Janeiro", "segmento": "Música Erudita", "valor_proposta": 766645.0, "UF": "RJ", "data_inicio": "2011-05-01", "projetos": 22, "mecanismo": "Mecenato", "data_termino": "2011-09-30", "proponente": "Equinox do Brasil - Consultoria em Projetos Culturais Ltda.", "valor_projeto": 186950.0, "area": "Música", "PRONAC": "108481"}, {"valor_aprovado": 1973730.0, "valor_captado": 0.0, "nome": "NOVO (titulo provisório)", "cgccpf": "04378171000100", "valor_solicitado": 2084780.0, "ano_projeto": "10", "enquadramento": "Artigo 26", "municipio": "São Paulo", "segmento": "Artes Integradas", "valor_proposta": 2084780.0, "UF": "SP", "data_inicio": "2011-02-01", "projetos": 23, "mecanismo": "Mecenato", "data_termino": "2012-02-01", "proponente": "Casa 5 Produções Artísticas ltda", "valor_projeto": 1973730.0, "area": "Música", "PRONAC": "108480"}, {"valor_aprovado": 559046.7, "valor_captado": 0.0, "nome": "Leblon Jazz Festival - Etapa bianual Rio de Janeiro", "cgccpf": "11819816000168", "valor_solicitado": 679176.7, "ano_projeto": "10", "enquadramento": "Artigo 26", "municipio": "Rio de Janeiro", "segmento": "Música Popular Cantada", "valor_proposta": 679176.7, "UF": "RJ", "data_inicio": "2010-12-01", "projetos": 24, "mecanismo": "Mecenato", "data_termino": "2011-11-01", "proponente": "VIACOM MARKETING PROMOCIONAL E ESPORTIVO LTDA", "valor_projeto": 559046.7, "area": "Música", "PRONAC": "108479"}, {"valor_aprovado": 457197.5, "valor_captado": 0.0, "nome": "Segunda às Segundas  - 2ª Temporada", "cgccpf": "04795835000136", "valor_solicitado": 482300.0, "ano_projeto": "10", "enquadramento": "Artigo 18", "municipio": "Sorocaba", "segmento": "Restauração/Bolsas", "valor_proposta": 482300.0, "UF": "SP", "data_inicio": "2011-01-13", "projetos": 25, "mecanismo": "Mecenato", "data_termino": "2013-12-31", "proponente": "MDA INTERNATIONAL LTDA - EPP", "valor_projeto": 457197.5, "area": "Artes Integradas", "PRONAC": "108478"}, {"valor_aprovado": 171408.75, "valor_captado": 171408.75, "nome": "Eugênio Gudin - Um Liberal em Estado Puro", "cgccpf": "28709731000120", "valor_solicitado": 309045.0, "ano_projeto": "10", "enquadramento": "Artigo 18", "municipio": "Rio de Janeiro", "segmento": "Edição de Livros", "valor_proposta": 309045.0, "UF": "RJ", "data_inicio": "2011-01-24", "projetos": 26, "mecanismo": "Mecenato", "data_termino": "2012-03-31", "proponente": "INSIGHT ENGENHARIA DE COMUNICAÇÃO & MARKETING LTDA", "valor_projeto": 171408.75, "area": "Humanidades", "PRONAC": "108477"}, {"valor_aprovado": 0.0, "valor_captado": 0.0, "nome": "Serra do Mar - História e Cultura (título provisório)", "cgccpf": "04762467000120", "valor_solicitado": 391030.2, "ano_projeto": "10", "enquadramento": "Nao enquadrado", "municipio": "São Paulo", "segmento": "Edição de Livros", "valor_proposta": 391030.2, "UF": "SP", "data_inicio": "2011-01-10", "projetos": 27, "mecanismo": "Mecenato", "data_termino": "2011-06-30", "proponente": "Editoria Origem Ltda - ME", "valor_projeto": 0.0, "area": "Humanidades", "PRONAC": "108476"}, {"valor_aprovado": 605848.0, "valor_captado": 0.0, "nome": "Criação, estreia e circulação do novo espetáculo da Quik Cia de Dança", "cgccpf": "05738007000129", "valor_solicitado": 608248.0, "ano_projeto": "10", "enquadramento": "Artigo 18", "municipio": "Nova Lima", "segmento": "Dança", "valor_proposta": 608248.0, "UF": "MG", "data_inicio": "2011-01-12", "projetos": 28, "mecanismo": "Mecenato", "data_termino": "2112-01-01", "proponente": "Q. C. DANÇA LTDA", "valor_projeto": 605848.0, "area": "Artes Cênicas", "PRONAC": "108475"}, {"valor_aprovado": 0.0, "valor_captado": 0.0, "nome": "Grupo Flor de Lis: Florindo e Frutificando na Terceira Idade", "cgccpf": "***186698**", "valor_solicitado": 0.0, "ano_projeto": "10", "enquadramento": "Nao enquadrado", "municipio": "Osasco", "segmento": "Cultura Popular", "valor_proposta": 0.0, "UF": "SP", "data_inicio": null, "projetos": 29, "mecanismo": "FNC", "data_termino": null, "proponente": "Edna Maria Santos", "valor_projeto": 0.0, "area": "Artes Integradas", "PRONAC": "108468"}, {"valor_aprovado": 0.0, "valor_captado": 0.0, "nome": "OLHARES DA MATURIDADE", "cgccpf": "09372135000152", "valor_solicitado": 0.0, "ano_projeto": "10", "enquadramento": "Nao enquadrado", "municipio": "Rio de Janeiro", "segmento": "Cultura Popular", "valor_proposta": 0.0, "UF": "RJ", "data_inicio": null, "projetos": 30, "mecanismo": "FNC", "data_termino": null, "proponente": "Associação Arte Nova Produções Culturais e Artísticas", "valor_projeto": 0.0, "area": "Artes Integradas", "PRONAC": "108467"}, {"valor_aprovado": 0.0, "valor_captado": 0.0, "nome": "Laboratório Cênico", "cgccpf": "***681677**", "valor_solicitado": 0.0, "ano_projeto": "10", "enquadramento": "Nao enquadrado", "municipio": "Rio de Janeiro", "segmento": "Cultura Popular", "valor_proposta": 0.0, "UF": "RJ", "data_inicio": null, "projetos": 31, "mecanismo": "FNC", "data_termino": null, "proponente": "Carlos Alberto da Silva Pimentel", "valor_projeto": 0.0, "area": "Artes Integradas", "PRONAC": "108466"}, {"valor_aprovado": 0.0, "valor_captado": 0.0, "nome": "Brasil de Cabelos Brancos", "cgccpf": "51561819000169", "valor_solicitado": 0.0, "ano_projeto": "10", "enquadramento": "Nao enquadrado", "municipio": "São Paulo", "segmento": "Cultura Popular", "valor_proposta": 0.0, "UF": "SP", "data_inicio": null, "projetos": 32, "mecanismo": "FNC", "data_termino": null, "proponente": "Cooperativa Paulista de Teatro", "valor_projeto": 0.0, "area": "Artes Integradas", "PRONAC": "108465"}, {"valor_aprovado": 0.0, "valor_captado": 0.0, "nome": "Dançando nas Nuvens", "cgccpf": "04097398000187", "valor_solicitado": 0.0, "ano_projeto": "10", "enquadramento": "Nao enquadrado", "municipio": "Macapá", "segmento": "Cultura Popular", "valor_proposta": 0.0, "UF": "AP", "data_inicio": null, "projetos": 33, "mecanismo": "FNC", "data_termino": null, "proponente": "Associação Carnavalesca Unidos do Novo Horizonte", "valor_projeto": 0.0, "area": "Artes Integradas", "PRONAC": "108464"}, {"valor_aprovado": 0.0, "valor_captado": 0.0, "nome": "I Toada dos Mestres de Cultura do Cariri", "cgccpf": "10321062000159", "valor_solicitado": 0.0, "ano_projeto": "10", "enquadramento": "Nao enquadrado", "municipio": "Juazeiro do Norte", "segmento": "Cultura Popular", "valor_proposta": 0.0, "UF": "CE", "data_inicio": null, "projetos": 34, "mecanismo": "FNC", "data_termino": null, "proponente": "Ong. Cia. Desabafo de Teatro", "valor_projeto": 0.0, "area": "Artes Integradas", "PRONAC": "108463"}, {"valor_aprovado": 0.0, "valor_captado": 0.0, "nome": "DE VOLTA ÀS RAÍZES", "cgccpf": "***078556**", "valor_solicitado": 0.0, "ano_projeto": "10", "enquadramento": "Nao enquadrado", "municipio": "Belo Horizonte", "segmento": "Cultura Popular", "valor_proposta": 0.0, "UF": "MG", "data_inicio": null, "projetos": 35, "mecanismo": "FNC", "data_termino": null, "proponente": "Maria do Rosário Alves Pereira", "valor_projeto": 0.0, "area": "Artes Integradas", "PRONAC": "108462"}, {"valor_aprovado": 0.0, "valor_captado": 0.0, "nome": "Cultura Popular na Terceira Idade", "cgccpf": "***969983**", "valor_solicitado": 0.0, "ano_projeto": "10", "enquadramento": "Nao enquadrado", "municipio": "São Luís", "segmento": "Cultura Popular", "valor_proposta": 0.0, "UF": "MA", "data_inicio": null, "projetos": 36, "mecanismo": "FNC", "data_termino": null, "proponente": "José Ribamar Carvalho", "valor_projeto": 0.0, "area": "Artes Integradas", "PRONAC": "108461"}, {"valor_aprovado": 0.0, "valor_captado": 0.0, "nome": "O TAL DO QUINTAL - UMA OPERETA CAIPIRA CONTEPORÂNEA", "cgccpf": "***353601**", "valor_solicitado": 0.0, "ano_projeto": "10", "enquadramento": "Nao enquadrado", "municipio": "Pirenópolis", "segmento": "Cultura Popular", "valor_proposta": 0.0, "UF": "GO", "data_inicio": null, "projetos": 37, "mecanismo": "FNC", "data_termino": null, "proponente": "Sebastião  Profeta do Amaral", "valor_projeto": 0.0, "area": "Artes Integradas", "PRONAC": "108460"}, {"valor_aprovado": 0.0, "valor_captado": 0.0, "nome": "A Arte, Viver e Conviver", "cgccpf": "***909089**", "valor_solicitado": 0.0, "ano_projeto": "10", "enquadramento": "Nao enquadrado", "municipio": "Bela Vista do Toldo", "segmento": "Cultura Popular", "valor_proposta": 0.0, "UF": "SC", "data_inicio": null, "projetos": 38, "mecanismo": "FNC", "data_termino": null, "proponente": "Olívio Pinto", "valor_projeto": 0.0, "area": "Artes Integradas", "PRONAC": "108459"}, {"valor_aprovado": 0.0, "valor_captado": 0.0, "nome": "Projeto Mais Vida", "cgccpf": "***811791**", "valor_solicitado": 0.0, "ano_projeto": "10", "enquadramento": "Nao enquadrado", "municipio": "Rio de Janeiro", "segmento": "Cultura Popular", "valor_proposta": 0.0, "UF": "RJ", "data_inicio": null, "projetos": 39, "mecanismo": "FNC", "data_termino": null, "proponente": "Dalma Campos Lucas", "valor_projeto": 0.0, "area": "Artes Integradas", "PRONAC": "108458"}, {"valor_aprovado": 0.0, "valor_captado": 0.0, "nome": "Saberes, Vivendo e reinventando a Vida, em busca da sustentabilidade.", "cgccpf": "***351013**", "valor_solicitado": 0.0, "ano_projeto": "10", "enquadramento": "Nao enquadrado", "municipio": "Senador Pompeu", "segmento": "Cultura Popular", "valor_proposta": 0.0, "UF": "CE", "data_inicio": null, "projetos": 40, "mecanismo": "FNC", "data_termino": null, "proponente": "Francisco Adriano Costa Souza", "valor_projeto": 0.0, "area": "Artes Integradas", "PRONAC": "108457"}, {"valor_aprovado": 0.0, "valor_captado": 0.0, "nome": "A Oficina de Psicomotricidade e Cinema da UNATI/UERJ apresenta: O ressentimento, o esquecimento e o riso: as metamorfoses da memória dos idosos.", "cgccpf": "***813767**", "valor_solicitado": 0.0, "ano_projeto": "10", "enquadramento": "Nao enquadrado", "municipio": "Rio de Janeiro", "segmento": "Cultura Popular", "valor_proposta": 0.0, "UF": "RJ", "data_inicio": null, "projetos": 41, "mecanismo": "FNC", "data_termino": null, "proponente": "Cristie de Moraes Campello", "valor_projeto": 0.0, "area": "Artes Integradas", "PRONAC": "108456"}, {"valor_aprovado": 0.0, "valor_captado": 0.0, "nome": "AS MENINAS DA DANÇA DO VENTRE", "cgccpf": "***458954**", "valor_solicitado": 0.0, "ano_projeto": "10", "enquadramento": "Nao enquadrado", "municipio": "Campina Grande", "segmento": "Cultura Popular", "valor_proposta": 0.0, "UF": "PB", "data_inicio": null, "projetos": 42, "mecanismo": "FNC", "data_termino": null, "proponente": "MÁRCIA MARGARIDA DA SILVA", "valor_projeto": 0.0, "area": "Artes Integradas", "PRONAC": "108455"}, {"valor_aprovado": 0.0, "valor_captado": 0.0, "nome": "GRUPO SORRIR E VIVER PROJETO: O TEATRO VAI À ESCOLA", "cgccpf": "***924498**", "valor_solicitado": 0.0, "ano_projeto": "10", "enquadramento": "Nao enquadrado", "municipio": "Vinhedo", "segmento": "Cultura Popular", "valor_proposta": 0.0, "UF": "SP", "data_inicio": null, "projetos": 43, "mecanismo": "FNC", "data_termino": null, "proponente": "Armando Vicente Junior", "valor_projeto": 0.0, "area": "Artes Integradas", "PRONAC": "108454"}, {"valor_aprovado": 0.0, "valor_captado": 0.0, "nome": "GUIA DA TERCEIRA IDADE - RJ : DO LIVRO ÀS REDES VIRTUAIS, 14 ANOS DE ARTE, INFORMAÇÃO, INCLUSÃO E PROMOÇÃO DA QUALIDADE DE VIDA DO IDOSO.", "cgccpf": "***105077**", "valor_solicitado": 0.0, "ano_projeto": "10", "enquadramento": "Nao enquadrado", "municipio": "Rio de Janeiro", "segmento": "Cultura Popular", "valor_proposta": 0.0, "UF": "RJ", "data_inicio": null, "projetos": 44, "mecanismo": "FNC", "data_termino": null, "proponente": "SABINE CAVALCANTE ", "valor_projeto": 0.0, "area": "Artes Integradas", "PRONAC": "108453"}, {"valor_aprovado": 0.0, "valor_captado": 0.0, "nome": "Ponto de Cultura Coco de Umbigada", "cgccpf": "08616844000173", "valor_solicitado": 0.0, "ano_projeto": "10", "enquadramento": "Nao enquadrado", "municipio": "Olinda", "segmento": "Cultura Popular", "valor_proposta": 0.0, "UF": "PE", "data_inicio": null, "projetos": 45, "mecanismo": "FNC", "data_termino": null, "proponente": "Centro Cultural Coco de Umbigada", "valor_projeto": 0.0, "area": "Artes Integradas", "PRONAC": "108452"}, {"valor_aprovado": 0.0, "valor_captado": 0.0, "nome": "Dançar é a Nova Ordem", "cgccpf": "04811352000188", "valor_solicitado": 0.0, "ano_projeto": "10", "enquadramento": "Nao enquadrado", "municipio": "Manaus", "segmento": "Cultura Popular", "valor_proposta": 0.0, "UF": "AM", "data_inicio": null, "projetos": 46, "mecanismo": "FNC", "data_termino": null, "proponente": "Associação das Donas de Casa do Estado do Amazonas", "valor_projeto": 0.0, "area": "Artes Integradas", "PRONAC": "108451"}, {"valor_aprovado": 0.0, "valor_captado": 0.0, "nome": "Clube da Melhor Idade, Luar de Prata", "cgccpf": "08805744000195", "valor_solicitado": 0.0, "ano_projeto": "10", "enquadramento": "Nao enquadrado", "municipio": "Timbaúba", "segmento": "Cultura Popular", "valor_proposta": 0.0, "UF": "PE", "data_inicio": null, "projetos": 47, "mecanismo": "FNC", "data_termino": null, "proponente": "Clube da melhor idade, Luar de Prata", "valor_projeto": 0.0, "area": "Artes Integradas", "PRONAC": "108450"}, {"valor_aprovado": 0.0, "valor_captado": 0.0, "nome": "Cultura e Vida: o brilho da arte através da memória da pessoa idosa.", "cgccpf": "07476737000124", "valor_solicitado": 0.0, "ano_projeto": "10", "enquadramento": "Nao enquadrado", "municipio": "Timóteo", "segmento": "Cultura Popular", "valor_proposta": 0.0, "UF": "MG", "data_inicio": null, "projetos": 48, "mecanismo": "FNC", "data_termino": null, "proponente": "CECAB", "valor_projeto": 0.0, "area": "Artes Integradas", "PRONAC": "108449"}, {"valor_aprovado": 0.0, "valor_captado": 0.0, "nome": "Universidade Aberta para o Envelhecimento Saudável - UNAPES, da Disciplina de Geriatria da Faculdade de Medicina da Universidade de São Paulo", "cgccpf": "05101991000112", "valor_solicitado": 0.0, "ano_projeto": "10", "enquadramento": "Nao enquadrado", "municipio": "São Paulo", "segmento": "Cultura Popular", "valor_proposta": 0.0, "UF": "SP", "data_inicio": null, "projetos": 49, "mecanismo": "FNC", "data_termino": null, "proponente": "Wilson Jacob Filho", "valor_projeto": 0.0, "area": "Artes Integradas", "PRONAC": "108448"}, {"valor_aprovado": 0.0, "valor_captado": 0.0, "nome": "SABER ORAL PRESERVADO: UMA AÇÃO DE RECONHECIMENTO DA CULTURA DA PESSOA IDOSA", "cgccpf": "07815380000161", "valor_solicitado": 0.0, "ano_projeto": "10", "enquadramento": "Nao enquadrado", "municipio": "Major Sales", "segmento": "Cultura Popular", "valor_proposta": 0.0, "UF": "RN", "data_inicio": null, "projetos": 50, "mecanismo": "FNC", "data_termino": null, "proponente": "Associação Comunitária Sócio-Cultural de Major Sales", "valor_projeto": 0.0, "area": "Artes Integradas", "PRONAC": "108447"}, {"valor_aprovado": 0.0, "valor_captado": 0.0, "nome": "Projeto de Valorização e Difusão dos Dramas de Guaramiranga", "cgccpf": "63366967000101", "valor_solicitado": 0.0, "ano_projeto": "10", "enquadramento": "Nao enquadrado", "municipio": "Guaramiranga", "segmento": "Cultura Popular", "valor_proposta": 0.0, "UF": "CE", "data_inicio": null, "projetos": 51, "mecanismo": "FNC", "data_termino": null, "proponente": "Associação dos Amigos da Arte de Guaramiranga", "valor_projeto": 0.0, "area": "Artes Integradas", "PRONAC": "108446"}, {"valor_aprovado": 0.0, "valor_captado": 0.0, "nome": "Clube da Maior Idade – Despertar para Viver", "cgccpf": "03218359000128", "valor_solicitado": 0.0, "ano_projeto": "10", "enquadramento": "Nao enquadrado", "municipio": "Prudentópolis", "segmento": "Cultura Popular", "valor_proposta": 0.0, "UF": "PR", "data_inicio": null, "projetos": 52, "mecanismo": "FNC", "data_termino": null, "proponente": "Clube da maior idade", "valor_projeto": 0.0, "area": "Artes Integradas", "PRONAC": "108445"}, {"valor_aprovado": 0.0, "valor_captado": 0.0, "nome": "BANDA INTEGRANDO GERAÇÕES", "cgccpf": "21126230000171", "valor_solicitado": 0.0, "ano_projeto": "10", "enquadramento": "Nao enquadrado", "municipio": "São José da Lapa", "segmento": "Cultura Popular", "valor_proposta": 0.0, "UF": "MG", "data_inicio": null, "projetos": 53, "mecanismo": "FNC", "data_termino": null, "proponente": "Corporação Musical São José /São José da Lapa - MG.", "valor_projeto": 0.0, "area": "Artes Integradas", "PRONAC": "108444"}, {"valor_aprovado": 0.0, "valor_captado": 0.0, "nome": "PROJETO SENHORA BONECA", "cgccpf": "04803394000177", "valor_solicitado": 0.0, "ano_projeto": "10", "enquadramento": "Nao enquadrado", "municipio": "São Paulo", "segmento": "Cultura Popular", "valor_proposta": 0.0, "UF": "SP", "data_inicio": null, "projetos": 54, "mecanismo": "FNC", "data_termino": null, "proponente": "INRI - Instituto Nacional de Renovação Integrado", "valor_projeto": 0.0, "area": "Artes Integradas", "PRONAC": "108443"}, {"valor_aprovado": 0.0, "valor_captado": 0.0, "nome": "Primeira opção: Terceira Idade", "cgccpf": "03527212000110", "valor_solicitado": 0.0, "ano_projeto": "10", "enquadramento": "Nao enquadrado", "municipio": "Guimarães", "segmento": "Cultura Popular", "valor_proposta": 0.0, "UF": "MA", "data_inicio": null, "projetos": 55, "mecanismo": "FNC", "data_termino": null, "proponente": "Associação Cultural e Folclórica Vimarense", "valor_projeto": 0.0, "area": "Artes Integradas", "PRONAC": "108442"}, {"valor_aprovado": 0.0, "valor_captado": 0.0, "nome": "Prejeto Viver Bem na Melhor Idade", "cgccpf": "63290571000128", "valor_solicitado": 0.0, "ano_projeto": "10", "enquadramento": "Nao enquadrado", "municipio": "Fortaleza", "segmento": "Cultura Popular", "valor_proposta": 0.0, "UF": "CE", "data_inicio": null, "projetos": 56, "mecanismo": "FNC", "data_termino": null, "proponente": "Associação Comunitária do Parque Jerusalém", "valor_projeto": 0.0, "area": "Artes Integradas", "PRONAC": "108441"}, {"valor_aprovado": 0.0, "valor_captado": 0.0, "nome": "Reciclando experiências. Oficinas de reciclagem, reaproveitamento de materiais e produção de papel artesanal", "cgccpf": "00627927000156", "valor_solicitado": 0.0, "ano_projeto": "10", "enquadramento": "Nao enquadrado", "municipio": "Brasília", "segmento": "Cultura Popular", "valor_proposta": 0.0, "UF": "DF", "data_inicio": null, "projetos": 57, "mecanismo": "FNC", "data_termino": null, "proponente": "Obras Assistenciais Centro Espírita Irmão Jorge", "valor_projeto": 0.0, "area": "Artes Integradas", "PRONAC": "108440"}, {"valor_aprovado": 0.0, "valor_captado": 0.0, "nome": "Grupo Menestréis da UnATI/UEA", "cgccpf": "03343080000176", "valor_solicitado": 0.0, "ano_projeto": "10", "enquadramento": "Nao enquadrado", "municipio": "Manaus", "segmento": "Cultura Popular", "valor_proposta": 0.0, "UF": "AM", "data_inicio": null, "projetos": 58, "mecanismo": "FNC", "data_termino": null, "proponente": "Fundação de Apoio Institucional Muraki", "valor_projeto": 0.0, "area": "Artes Integradas", "PRONAC": "108439"}, {"valor_aprovado": 0.0, "valor_captado": 0.0, "nome": "Coral Integração da UnATI UEA", "cgccpf": "03343080000176", "valor_solicitado": 0.0, "ano_projeto": "10", "enquadramento": "Nao enquadrado", "municipio": "Manaus", "segmento": "Cultura Popular", "valor_proposta": 0.0, "UF": "AM", "data_inicio": null, "projetos": 59, "mecanismo": "FNC", "data_termino": null, "proponente": "Fundação de Apoio Institucional Muraki", "valor_projeto": 0.0, "area": "Artes Integradas", "PRONAC": "108438"}, {"valor_aprovado": 0.0, "valor_captado": 0.0, "nome": "Projeto Vem Dançar", "cgccpf": "87612784000197", "valor_solicitado": 0.0, "ano_projeto": "10", "enquadramento": "Nao enquadrado", "municipio": "Alecrim", "segmento": "Cultura Popular", "valor_proposta": 0.0, "UF": "RS", "data_inicio": null, "projetos": 60, "mecanismo": "FNC", "data_termino": null, "proponente": "Prefeitura Municipal de Alecrim", "valor_projeto": 0.0, "area": "Artes Integradas", "PRONAC": "108437"}, {"valor_aprovado": 0.0, "valor_captado": 0.0, "nome": "Associação Artística Cultural Língua Solta", "cgccpf": "06945399000160", "valor_solicitado": 0.0, "ano_projeto": "10", "enquadramento": "Nao enquadrado", "municipio": "Santana", "segmento": "Cultura Popular", "valor_proposta": 0.0, "UF": "AP", "data_inicio": null, "projetos": 61, "mecanismo": "FNC", "data_termino": null, "proponente": "Grupo Teatral Língua Solta", "valor_projeto": 0.0, "area": "Artes Integradas", "PRONAC": "108436"}, {"valor_aprovado": 0.0, "valor_captado": 0.0, "nome": "Arte Cultura na 3ª idade, Um exercício de cidadania", "cgccpf": "05455555000141", "valor_solicitado": 0.0, "ano_projeto": "10", "enquadramento": "Nao enquadrado", "municipio": "Milagres", "segmento": "Cultura Popular", "valor_proposta": 0.0, "UF": "CE", "data_inicio": null, "projetos": 62, "mecanismo": "FNC", "data_termino": null, "proponente": "Associação Comunitária de Milagres - ACOM", "valor_projeto": 0.0, "area": "Artes Integradas", "PRONAC": "108435"}, {"valor_aprovado": 0.0, "valor_captado": 0.0, "nome": "Projeto Social, A Dança da Vida", "cgccpf": "09186774000123", "valor_solicitado": 0.0, "ano_projeto": "10", "enquadramento": "Nao enquadrado", "municipio": "Porto Alegre", "segmento": "Cultura Popular", "valor_proposta": 0.0, "UF": "RS", "data_inicio": null, "projetos": 63, "mecanismo": "FNC", "data_termino": null, "proponente": "Zapata Filmes LTDA", "valor_projeto": 0.0, "area": "Artes Integradas", "PRONAC": "108434"}, {"valor_aprovado": 0.0, "valor_captado": 0.0, "nome": "Feliz Idade em Ação e Cultura em Auto Padrão", "cgccpf": "11407662000105", "valor_solicitado": 0.0, "ano_projeto": "10", "enquadramento": "Nao enquadrado", "municipio": "Novo Cruzeiro", "segmento": "Cultura Popular", "valor_proposta": 0.0, "UF": "MG", "data_inicio": null, "projetos": 64, "mecanismo": "FNC", "data_termino": null, "proponente": "Associação de Mulheres da Economia Solidária de Novo Cruzeiro", "valor_projeto": 0.0, "area": "Artes Integradas", "PRONAC": "108433"}, {"valor_aprovado": 0.0, "valor_captado": 0.0, "nome": "o Show da Vida", "cgccpf": "06315116000104", "valor_solicitado": 0.0, "ano_projeto": "10", "enquadramento": "Nao enquadrado", "municipio": "Fortaleza", "segmento": "Cultura Popular", "valor_proposta": 0.0, "UF": "CE", "data_inicio": null, "projetos": 65, "mecanismo": "FNC", "data_termino": null, "proponente": "Associação Coral Vozes do Outono", "valor_projeto": 0.0, "area": "Artes Integradas", "PRONAC": "108432"}, {"valor_aprovado": 0.0, "valor_captado": 0.0, "nome": "MARACATU: BATUQUE DO CORAÇÃO", "cgccpf": "69129880000105", "valor_solicitado": 0.0, "ano_projeto": "10", "enquadramento": "Nao enquadrado", "municipio": "São Paulo", "segmento": "Cultura Popular", "valor_proposta": 0.0, "UF": "SP", "data_inicio": null, "projetos": 66, "mecanismo": "FNC", "data_termino": null, "proponente": "N.C.I Coraçã'o Materno", "valor_projeto": 0.0, "area": "Artes Integradas", "PRONAC": "108431"}, {"valor_aprovado": 0.0, "valor_captado": 0.0, "nome": "A História Somos Nós", "cgccpf": "04206361000140", "valor_solicitado": 0.0, "ano_projeto": "10", "enquadramento": "Nao enquadrado", "municipio": "Dionísio Cerqueira", "segmento": "Cultura Popular", "valor_proposta": 0.0, "UF": "SC", "data_inicio": null, "projetos": 67, "mecanismo": "FNC", "data_termino": null, "proponente": "Companhia de Teatro Arco-Íris", "valor_projeto": 0.0, "area": "Artes Integradas", "PRONAC": "108429"}, {"valor_aprovado": 0.0, "valor_captado": 0.0, "nome": "Projeto  Vozes da Cidade de Deus – vozes unidas pelo canto", "cgccpf": "03483529000100", "valor_solicitado": 0.0, "ano_projeto": "10", "enquadramento": "Nao enquadrado", "municipio": "Rio de Janeiro", "segmento": "Cultura Popular", "valor_proposta": 0.0, "UF": "RJ", "data_inicio": null, "projetos": 68, "mecanismo": "FNC", "data_termino": null, "proponente": "Casa de Santa Ana - Centro Dia Santa", "valor_projeto": 0.0, "area": "Artes Integradas", "PRONAC": "108428"}, {"valor_aprovado": 0.0, "valor_captado": 0.0, "nome": "Dançando na Melhor Idade.", "cgccpf": "05984677000125", "valor_solicitado": 0.0, "ano_projeto": "10", "enquadramento": "Nao enquadrado", "municipio": "Pontal do Paraná", "segmento": "Cultura Popular", "valor_proposta": 0.0, "UF": "PR", "data_inicio": null, "projetos": 69, "mecanismo": "FNC", "data_termino": null, "proponente": "Grupo de Dança Coração de Pontal.", "valor_projeto": 0.0, "area": "Artes Integradas", "PRONAC": "108427"}, {"valor_aprovado": 0.0, "valor_captado": 0.0, "nome": "Dançando com Arte na Melhor Idade", "cgccpf": "04399292000138", "valor_solicitado": 0.0, "ano_projeto": "10", "enquadramento": "Nao enquadrado", "municipio": "Fundão", "segmento": "Cultura Popular", "valor_proposta": 0.0, "UF": "ES", "data_inicio": null, "projetos": 70, "mecanismo": "FNC", "data_termino": null, "proponente": "Adoris Raymundo Helmet", "valor_projeto": 0.0, "area": "Artes Integradas", "PRONAC": "108426"}, {"valor_aprovado": 0.0, "valor_captado": 0.0, "nome": "Grupo Folclórico Lindroamor Axé", "cgccpf": "03638125000130", "valor_solicitado": 0.0, "ano_projeto": "10", "enquadramento": "Nao enquadrado", "municipio": "São Francisco do Conde", "segmento": "Cultura Popular", "valor_proposta": 0.0, "UF": "BA", "data_inicio": null, "projetos": 71, "mecanismo": "FNC", "data_termino": null, "proponente": "Grupo Folclórico Lindroamor Axé", "valor_projeto": 0.0, "area": "Artes Integradas", "PRONAC": "108425"}, {"valor_aprovado": 0.0, "valor_captado": 0.0, "nome": "DU EU SERTÃO", "cgccpf": "***746713**", "valor_solicitado": 0.0, "ano_projeto": "10", "enquadramento": "Nao enquadrado", "municipio": "Teresina", "segmento": "Cultura Popular", "valor_proposta": 0.0, "UF": "PI", "data_inicio": null, "projetos": 72, "mecanismo": "FNC", "data_termino": null, "proponente": "LUIS CARLOS MACHADO DO VALE", "valor_projeto": 0.0, "area": "Artes Integradas", "PRONAC": "108424"}, {"valor_aprovado": 0.0, "valor_captado": 0.0, "nome": "CARLOS FARIAS: cantando a vida com as lavadeiras de almenara", "cgccpf": "***410816**", "valor_solicitado": 0.0, "ano_projeto": "10", "enquadramento": "Nao enquadrado", "municipio": "Belo Horizonte", "segmento": "Cultura Popular", "valor_proposta": 0.0, "UF": "MG", "data_inicio": null, "projetos": 73, "mecanismo": "FNC", "data_termino": null, "proponente": "Carlos Augusto de Farias", "valor_projeto": 0.0, "area": "Artes Integradas", "PRONAC": "108423"}, {"valor_aprovado": 0.0, "valor_captado": 0.0, "nome": "Preservação, valorização e transmissão dos conhecimentos e da memória dos mais antigos mestres-salas e porta-bandeiras do carnaval carioca", "cgccpf": "00148384000194", "valor_solicitado": 0.0, "ano_projeto": "10", "enquadramento": "Nao enquadrado", "municipio": "Rio de Janeiro", "segmento": "Cultura Popular", "valor_proposta": 0.0, "UF": "RJ", "data_inicio": null, "projetos": 74, "mecanismo": "FNC", "data_termino": null, "proponente": "Escola de Mestre-Sala, Porta-Bandeira e Porta-Estandarte/Rj", "valor_projeto": 0.0, "area": "Artes Integradas", "PRONAC": "108422"}, {"valor_aprovado": 0.0, "valor_captado": 0.0, "nome": "Revitalização da Cultura Paiter Surui", "cgccpf": "03242372000112", "valor_solicitado": 0.0, "ano_projeto": "10", "enquadramento": "Nao enquadrado", "municipio": "Cacoal", "segmento": "Cultura Popular", "valor_proposta": 0.0, "UF": "RO", "data_inicio": null, "projetos": 75, "mecanismo": "FNC", "data_termino": null, "proponente": "Associação Gãbgir do Povo Indígena Surui", "valor_projeto": 0.0, "area": "Artes Integradas", "PRONAC": "108421"}, {"valor_aprovado": 0.0, "valor_captado": 0.0, "nome": "Grupo Teatral GREAMARCEN da Feliz Idade", "cgccpf": "***069866**", "valor_solicitado": 0.0, "ano_projeto": "10", "enquadramento": "Nao enquadrado", "municipio": "Novo Cruzeiro", "segmento": "Cultura Popular", "valor_proposta": 0.0, "UF": "MG", "data_inicio": null, "projetos": 76, "mecanismo": "FNC", "data_termino": null, "proponente": "Marley Christino Navarro", "valor_projeto": 0.0, "area": "Artes Integradas", "PRONAC": "108420"}, {"valor_aprovado": 0.0, "valor_captado": 0.0, "nome": "Raizes de Ipanema - MG", "cgccpf": "***691416**", "valor_solicitado": 0.0, "ano_projeto": "10", "enquadramento": "Nao enquadrado", "municipio": "Ipanema", "segmento": "Cultura Popular", "valor_proposta": 0.0, "UF": "MG", "data_inicio": null, "projetos": 77, "mecanismo": "FNC", "data_termino": null, "proponente": "João Gomes de Oliveira", "valor_projeto": 0.0, "area": "Artes Integradas", "PRONAC": "108419"}, {"valor_aprovado": 0.0, "valor_captado": 0.0, "nome": "Centro de Convivência dos Idosos", "cgccpf": "***802174**", "valor_solicitado": 0.0, "ano_projeto": "10", "enquadramento": "Nao enquadrado", "municipio": "Bezerros", "segmento": "Cultura Popular", "valor_proposta": 0.0, "UF": "PE", "data_inicio": null, "projetos": 78, "mecanismo": "FNC", "data_termino": null, "proponente": "Marlom Meirelles Silva Nascimento", "valor_projeto": 0.0, "area": "Artes Integradas", "PRONAC": "108418"}, {"valor_aprovado": 0.0, "valor_captado": 0.0, "nome": "GRUPO CULTURAL DA TERCEIRA IDADE - GCTI - PROJETO SAMBA DAS GANHADEIRAS - Mulher Negra na Bahia no Século XIX", "cgccpf": "***370725**", "valor_solicitado": 0.0, "ano_projeto": "10", "enquadramento": "Nao enquadrado", "municipio": "Salvador", "segmento": "Cultura Popular", "valor_proposta": 0.0, "UF": "BA", "data_inicio": null, "projetos": 79, "mecanismo": "FNC", "data_termino": null, "proponente": "Silvia Rita Santos de Cerqueira", "valor_projeto": 0.0, "area": "Artes Integradas", "PRONAC": "108417"}, {"valor_aprovado": 0.0, "valor_captado": 0.0, "nome": "Criatividade: Vivenciando Um Novo Tempo", "cgccpf": "***061134**", "valor_solicitado": 0.0, "ano_projeto": "10", "enquadramento": "Nao enquadrado", "municipio": "Graça", "segmento": "Cultura Popular", "valor_proposta": 0.0, "UF": "CE", "data_inicio": null, "projetos": 80, "mecanismo": "FNC", "data_termino": null, "proponente": "TATIANA RIBEIRO COSTA", "valor_projeto": 0.0, "area": "Artes Integradas", "PRONAC": "108416"}, {"valor_aprovado": 0.0, "valor_captado": 0.0, "nome": "(Violeiro/cantador e mestre de dança da catira Galvãozinho da dupla caipira Galvan e Galvãozinho)", "cgccpf": "***986991**", "valor_solicitado": 0.0, "ano_projeto": "10", "enquadramento": "Nao enquadrado", "municipio": "Brasília", "segmento": "Cultura Popular", "valor_proposta": 0.0, "UF": "GO", "data_inicio": null, "projetos": 81, "mecanismo": "FNC", "data_termino": null, "proponente": "Volmi Batista da Silva", "valor_projeto": 0.0, "area": "Artes Integradas", "PRONAC": "108415"}, {"valor_aprovado": 0.0, "valor_captado": 0.0, "nome": "TOQUE SEM RETOQUE", "cgccpf": "***607817**", "valor_solicitado": 0.0, "ano_projeto": "10", "enquadramento": "Nao enquadrado", "municipio": "Niterói", "segmento": "Cultura Popular", "valor_proposta": 0.0, "UF": "RJ", "data_inicio": null, "projetos": 82, "mecanismo": "FNC", "data_termino": null, "proponente": "davy alexandrisky", "valor_projeto": 0.0, "area": "Artes Integradas", "PRONAC": "108414"}, {"valor_aprovado": 0.0, "valor_captado": 0.0, "nome": "DANÇA COM ALEGRIA: CULTURA, ARTE E INCLUSÃO DA PESSOA IDOSA.", "cgccpf": "***976259**", "valor_solicitado": 0.0, "ano_projeto": "10", "enquadramento": "Nao enquadrado", "municipio": "Pinhalzinho", "segmento": "Cultura Popular", "valor_proposta": 0.0, "UF": "SC", "data_inicio": null, "projetos": 83, "mecanismo": "FNC", "data_termino": null, "proponente": "FABIANE BONETI", "valor_projeto": 0.0, "area": "Artes Integradas", "PRONAC": "108413"}, {"valor_aprovado": 0.0, "valor_captado": 0.0, "nome": "MELHOR IDADE NO PONTO", "cgccpf": "01268704000102", "valor_solicitado": 0.0, "ano_projeto": "10", "enquadramento": "Nao enquadrado", "municipio": "Granja", "segmento": "Cultura Popular", "valor_proposta": 0.0, "UF": "CE", "data_inicio": null, "projetos": 84, "mecanismo": "FNC", "data_termino": null, "proponente": "Sociedade Cultural Granjense", "valor_projeto": 0.0, "area": "Artes Integradas", "PRONAC": "108412"}, {"valor_aprovado": 0.0, "valor_captado": 0.0, "nome": "Grupo de Canto Vozes da Aldeia", "cgccpf": "10417948000109", "valor_solicitado": 0.0, "ano_projeto": "10", "enquadramento": "Nao enquadrado", "municipio": "Gravataí", "segmento": "Cultura Popular", "valor_proposta": 0.0, "UF": "RS", "data_inicio": null, "projetos": 85, "mecanismo": "FNC", "data_termino": null, "proponente": "Associação Beneficiente Grupo de Canto Vozes da Aldeia", "valor_projeto": 0.0, "area": "Artes Integradas", "PRONAC": "108410"}, {"valor_aprovado": 0.0, "valor_captado": 0.0, "nome": "Vida ativa na melhor idade.", "cgccpf": "03949019000177", "valor_solicitado": 0.0, "ano_projeto": "10", "enquadramento": "Nao enquadrado", "municipio": "Mato Queimado", "segmento": "Cultura Popular", "valor_proposta": 0.0, "UF": "RS", "data_inicio": null, "projetos": 86, "mecanismo": "FNC", "data_termino": null, "proponente": "Clube Viver e Partilhar da Terceira Idade", "valor_projeto": 0.0, "area": "Artes Integradas", "PRONAC": "108409"}, {"valor_aprovado": 0.0, "valor_captado": 0.0, "nome": "Do Mundo Iletrado ao Mundo Letrado e Digital, inclusão digital para a terceira idade (Meta do Projeto Oficinas Pedagógicas de Prosa, Poesia e teatro)", "cgccpf": "07243476000100", "valor_solicitado": 0.0, "ano_projeto": "10", "enquadramento": "Nao enquadrado", "municipio": "Belo Horizonte", "segmento": "Cultura Popular", "valor_proposta": 0.0, "UF": "MG", "data_inicio": null, "projetos": 87, "mecanismo": "FNC", "data_termino": null, "proponente": "Instituto Cidadania Educação e Cultura", "valor_projeto": 0.0, "area": "Artes Integradas", "PRONAC": "108408"}, {"valor_aprovado": 0.0, "valor_captado": 0.0, "nome": "Entre o passado e o futuro, o resgate e a inclução Cultural", "cgccpf": "05842465000103", "valor_solicitado": 0.0, "ano_projeto": "10", "enquadramento": "Nao enquadrado", "municipio": "Felixlândia", "segmento": "Cultura Popular", "valor_proposta": 0.0, "UF": "MG", "data_inicio": null, "projetos": 88, "mecanismo": "FNC", "data_termino": null, "proponente": "Clube da Terceira Idade de Felixlândia", "valor_projeto": 0.0, "area": "Artes Integradas", "PRONAC": "108407"}, {"valor_aprovado": 0.0, "valor_captado": 0.0, "nome": "Cultura de primeira na terceira Idade", "cgccpf": "41009036000113", "valor_solicitado": 0.0, "ano_projeto": "10", "enquadramento": "Nao enquadrado", "municipio": "Moreno", "segmento": "Cultura Popular", "valor_proposta": 0.0, "UF": "PE", "data_inicio": null, "projetos": 89, "mecanismo": "FNC", "data_termino": null, "proponente": "grupo de idosos raio de sol", "valor_projeto": 0.0, "area": "Artes Integradas", "PRONAC": "108406"}, {"valor_aprovado": 0.0, "valor_captado": 0.0, "nome": "Os Direitos dos Idosos", "cgccpf": "02483227000160", "valor_solicitado": 0.0, "ano_projeto": "10", "enquadramento": "Nao enquadrado", "municipio": "Brasília", "segmento": "Cultura Popular", "valor_proposta": 0.0, "UF": "DF", "data_inicio": null, "projetos": 90, "mecanismo": "FNC", "data_termino": null, "proponente": "Associação Artística Mapati", "valor_projeto": 0.0, "area": "Artes Integradas", "PRONAC": "108405"}, {"valor_aprovado": 0.0, "valor_captado": 0.0, "nome": "TEATRO VELHOS TALENTOS", "cgccpf": "16697088000182", "valor_solicitado": 0.0, "ano_projeto": "10", "enquadramento": "Nao enquadrado", "municipio": "Betim", "segmento": "Cultura Popular", "valor_proposta": 0.0, "UF": "MG", "data_inicio": null, "projetos": 91, "mecanismo": "FNC", "data_termino": null, "proponente": "APROMIV - Associação de Proteção a Maternidade, Infância e Velhice", "valor_projeto": 0.0, "area": "Artes Integradas", "PRONAC": "108404"}, {"valor_aprovado": 0.0, "valor_captado": 0.0, "nome": "GRUPO FOLCLÓRICO ANCIÔES DA ARTE", "cgccpf": "10340889000100", "valor_solicitado": 0.0, "ano_projeto": "10", "enquadramento": "Nao enquadrado", "municipio": "São José do Campestre", "segmento": "Cultura Popular", "valor_proposta": 0.0, "UF": "RN", "data_inicio": null, "projetos": 92, "mecanismo": "FNC", "data_termino": null, "proponente": "Associação dos amigos da casa de cultura palácio borborema potiguar", "valor_projeto": 0.0, "area": "Artes Integradas", "PRONAC": "108403"}, {"valor_aprovado": 0.0, "valor_captado": 0.0, "nome": "Associação Comunitária dos Idosos de Rubim", "cgccpf": "09058004000103", "valor_solicitado": 0.0, "ano_projeto": "10", "enquadramento": "Nao enquadrado", "municipio": "Rubim", "segmento": "Cultura Popular", "valor_proposta": 0.0, "UF": "MG", "data_inicio": null, "projetos": 93, "mecanismo": "FNC", "data_termino": null, "proponente": "Associação Comunitária dos Idosos de Rubim", "valor_projeto": 0.0, "area": "Artes Integradas", "PRONAC": "108402"}, {"valor_aprovado": 0.0, "valor_captado": 0.0, "nome": "Encontro Pernambucano de Coco", "cgccpf": "08894801000150", "valor_solicitado": 0.0, "ano_projeto": "10", "enquadramento": "Nao enquadrado", "municipio": "Cabo de Santo Agostinho", "segmento": "Cultura Popular", "valor_proposta": 0.0, "UF": "PE", "data_inicio": null, "projetos": 94, "mecanismo": "FNC", "data_termino": null, "proponente": "Centro Cultura Farol da Vila", "valor_projeto": 0.0, "area": "Artes Integradas", "PRONAC": "108401"}, {"valor_aprovado": 0.0, "valor_captado": 0.0, "nome": "Balanço das Ondas", "cgccpf": "03309573000190", "valor_solicitado": 0.0, "ano_projeto": "10", "enquadramento": "Nao enquadrado", "municipio": "Balneário Camboriú", "segmento": "Cultura Popular", "valor_proposta": 0.0, "UF": "SC", "data_inicio": null, "projetos": 95, "mecanismo": "FNC", "data_termino": null, "proponente": "Associação Grupo 3ª Idade Balanço das Ondas de Balneário Camuriú", "valor_projeto": 0.0, "area": "Artes Integradas", "PRONAC": "108400"}, {"valor_aprovado": 0.0, "valor_captado": 0.0, "nome": "Reisado de Zabelê", "cgccpf": "05919387000106", "valor_solicitado": 0.0, "ano_projeto": "10", "enquadramento": "Nao enquadrado", "municipio": "Zabelê", "segmento": "Cultura Popular", "valor_proposta": 0.0, "UF": "PB", "data_inicio": null, "projetos": 96, "mecanismo": "FNC", "data_termino": null, "proponente": "Associação Cultural de Zabelê (ASCUZA)", "valor_projeto": 0.0, "area": "Artes Integradas", "PRONAC": "108399"}, {"valor_aprovado": 0.0, "valor_captado": 0.0, "nome": "ASAPEG", "cgccpf": "88145354000175", "valor_solicitado": 0.0, "ano_projeto": "10", "enquadramento": "Nao enquadrado", "municipio": "Gravataí", "segmento": "Cultura Popular", "valor_proposta": 0.0, "UF": "RS", "data_inicio": null, "projetos": 97, "mecanismo": "FNC", "data_termino": null, "proponente": "Associação dos Aposentados e Pensionistas de Gravataí", "valor_projeto": 0.0, "area": "Artes Integradas", "PRONAC": "108398"}, {"valor_aprovado": 0.0, "valor_captado": 0.0, "nome": "Caravana Cultural - Faça sua melhor idade", "cgccpf": "09037255000101", "valor_solicitado": 0.0, "ano_projeto": "10", "enquadramento": "Nao enquadrado", "municipio": "Itabaiana", "segmento": "Cultura Popular", "valor_proposta": 0.0, "UF": "PB", "data_inicio": null, "projetos": 98, "mecanismo": "FNC", "data_termino": null, "proponente": "Associação Alegria de Viver Vovó Olívia - AAVVO", "valor_projeto": 0.0, "area": "Artes Integradas", "PRONAC": "108397"}, {"valor_aprovado": 0.0, "valor_captado": 0.0, "nome": "Baile da Melhor Idade", "cgccpf": "58483041000166", "valor_solicitado": 0.0, "ano_projeto": "10", "enquadramento": "Nao enquadrado", "municipio": "Guarulhos", "segmento": "Cultura Popular", "valor_proposta": 0.0, "UF": "SP", "data_inicio": null, "projetos": 99, "mecanismo": "FNC", "data_termino": null, "proponente": "Corporação Musical Lira de Guarulhos", "valor_projeto": 0.0, "area": "Artes Integradas", "PRONAC": "108396"}]}